dokuWikiDumper/__init__.py
dokuWikiDumper/__main__.py
dokuWikiDumper/dump/content/content.py
dokuWikiDumper/dump/content/revisions.py
dokuWikiDumper/dump/content/titles.py
dokuWikiDumper/dump/doku_dumper.py
dokuWikiDumper/dump/html/html.py
dokuWikiDumper/dump/info/info.py
dokuWikiDumper/dump/media/media.py
dokuWikiDumper/dump/pdf/pdf.py
dokuWikiDumper/exceptions.py
dokuWikiDumper/utils/config.py
dokuWikiDumper/utils/delay.py
dokuWikiDumper/utils/dump_lock.py
dokuWikiDumper/utils/ia_checker.py
dokuWikiDumper/utils/patch.py
dokuWikiDumper/utils/session.py
dokuWikiDumper/utils/test_util.py
dokuWikiDumper/utils/util.py
dokuWikiDumper/version.py
dokuWikiDumper/version_check.py
dokuWikiUploader/__init__.py
dokuWikiUploader/__main__.py
dokuWikiUploader/__version__.py
dokuWikiUploader/uploader.py
dokuwikidumper-0.2.4.dist-info/METADATA
dokuwikidumper-0.2.4.dist-info/WHEEL
dokuwikidumper-0.2.4.dist-info/entry_points.txt
dokuwikidumper-0.2.4.dist-info/licenses/LICENSE.md
dokuwikidumper-0.2.4.dist-info/RECORD
