Metadata-Version: 2.1
Name: dokuWikiDumper
Version: 0.2.4
Summary: A tool for archiving DokuWiki
Author-Email: yzqzss <yzqzss@yandex.com>
License: GPL-3.0
Project-URL: Bug Tracker, https://github.com/saveweb/dokuwiki-dumper/issues
Project-URL: repository, https://github.com/saveweb/dokuwiki-dumper/
Requires-Python: <4.0,>=3.9
Requires-Dist: requests<3.0.0,>=2.32.2
Requires-Dist: beautifulsoup4<5.0.0,>=4.13.4
Requires-Dist: lxml<6.0.0,>=5.4.0
Requires-Dist: internetarchive<6.0.0,>=5.4.0
Requires-Dist: rich<15.0.0,>=14.0.0
Requires-Dist: python-slugify<9.0.0,>=8.0.4
Requires-Dist: typing-extensions<5.0.0,>=4.13.2
